crcreditum/__init__.py
crcreditum/cli.py
crcreditum/py.typed
crcreditum/core/__init__.py
crcreditum/core/config.py
crcreditum/models/__init__.py
crcreditum/models/basel.py
crcreditum/models/cra.py
crcreditum/models/explainability.py
crcreditum/models/stress_testing.py
crcreditum/schemas/__init__.py
crcreditum/schemas/assessment.py
crcreditum/schemas/corporate.py
crcreditum/schemas/enums.py
crcreditum/schemas/individual.py
crcreditum/schemas/legacy.py
crcreditum-1.0.6.dist-info/licenses/LICENSE
crcreditum-1.0.6.dist-info/METADATA
crcreditum-1.0.6.dist-info/WHEEL
crcreditum-1.0.6.dist-info/entry_points.txt
crcreditum-1.0.6.dist-info/top_level.txt
crcreditum-1.0.6.dist-info/RECORD
