Metadata-Version: 2.4
Name: crcreditum
Version: 1.0.6
Summary: Advanced Credit Risk Assessment with CRA Compliance and Basel III Integration
Home-page: https://github.com/crcreditum/crcreditum
Author: CRCreditum Team
Author-email: CRCreditum Team <support@crcreditum.com>
License: MIT
Project-URL: Documentation, https://docs.crcreditum.com
Project-URL: Repository, https://github.com/crcreditum/crcreditum
Project-URL: Bug Tracker, https://github.com/crcreditum/crcreditum/issues
Keywords: credit risk,basel iii,cra compliance,financial modeling,stress testing,explainable ai,regulatory compliance
Classifier: Development Status :: 5 - Production/Stable
Classifier: Intended Audience :: Financial and Insurance Industry
Classifier: Topic :: Office/Business :: Financial :: Investment
Classifier: License :: OSI Approved :: MIT License
Classifier: Programming Language :: Python :: 3
Classifier: Programming Language :: Python :: 3.8
Classifier: Programming Language :: Python :: 3.9
Classifier: Programming Language :: Python :: 3.10
Classifier: Programming Language :: Python :: 3.11
Classifier: Operating System :: OS Independent
Requires-Python: >=3.8
License-File: LICENSE
Requires-Dist: numpy>=1.21.0
Requires-Dist: pandas>=1.3.0
Requires-Dist: scikit-learn>=1.1.0
Requires-Dist: scipy>=1.7.0
Requires-Dist: pydantic>=1.10.0
Requires-Dist: python-dateutil>=2.8.0
Requires-Dist: typing-extensions>=4.0.0
Requires-Dist: requests>=2.28.0
Requires-Dist: click>=8.0.0
Requires-Dist: matplotlib>=3.5.0
Requires-Dist: plotly>=5.10.0
Requires-Dist: shap>=0.41.0
Requires-Dist: xgboost>=1.6.0
Requires-Dist: lightgbm>=3.3.0
Provides-Extra: dev
Requires-Dist: pytest>=7.0.0; extra == "dev"
Requires-Dist: pytest-cov>=4.0.0; extra == "dev"
Requires-Dist: black>=22.0.0; extra == "dev"
Requires-Dist: flake8>=5.0.0; extra == "dev"
Requires-Dist: mypy>=1.0.0; extra == "dev"
Requires-Dist: pre-commit>=2.20.0; extra == "dev"
Provides-Extra: docs
Requires-Dist: sphinx>=5.0.0; extra == "docs"
Requires-Dist: sphinx-rtd-theme>=1.0.0; extra == "docs"
Requires-Dist: sphinx-autodoc-typehints>=1.19.0; extra == "docs"
Provides-Extra: ml
Requires-Dist: catboost>=1.1.0; extra == "ml"
Requires-Dist: optuna>=3.0.0; extra == "ml"
Dynamic: author
Dynamic: home-page
Dynamic: license-file
Dynamic: requires-python
